src/__init__.py
src/character.py
src/data/stages.json
src/main.py
src/model.py
terminal_sokoban-1.1.0.dist-info/LICENSE
terminal_sokoban-1.1.0.dist-info/METADATA
terminal_sokoban-1.1.0.dist-info/WHEEL
terminal_sokoban-1.1.0.dist-info/entry_points.txt
terminal_sokoban-1.1.0.dist-info/RECORD
