Metadata-Version: 2.1
Name: terminal-sokoban
Version: 1.1.0
Summary: A terminal based Sokoban game interface
Home-page: https://github.com/IamAbbey/terminal-sokoban
License: MIT
Keywords: sokoban,terminal,console,game
Author: Abiodun Sotunde
Author-email: sotundeabiodun00@gmail.com
Requires-Python: >=3.12,<3.13
Classifier: Environment :: Console
Classifier: Intended Audience :: End Users/Desktop
Classifier: License :: OSI Approved :: MIT License
Classifier: Operating System :: POSIX
Classifier: Programming Language :: Python :: 3
Classifier: Programming Language :: Python :: 3.12
Classifier: Topic :: Games/Entertainment :: Puzzle Games
Requires-Dist: blessed (>=1.20.0,<2.0.0)
Requires-Dist: pydantic (>=2.6.4,<3.0.0)
Project-URL: Repository, https://github.com/IamAbbey/terminal-sokoban
